bashparser/__init__.py
bashparser/ast.py
bashparser/chunk.py
bashparser/commands.py
bashparser/complexity.py
bashparser/functions.py
bashparser/generalize.py
bashparser/template.py
bashparser/unroll.py
bashparser/variables.py
bashparser/test/__init__.py
bashparser/test/test_ast.py
bashparser/test/test_chunk.py
bashparser/test/test_command.py
bashparser/test/test_features.py
bashparser/test/test_functions.py
bashparser/test/test_unroll.py
bashparser/test/test_variable.py
bashparser-0.17.dist-info/LICENSE.txt
bashparser-0.17.dist-info/METADATA
bashparser-0.17.dist-info/WHEEL
bashparser-0.17.dist-info/entry_points.txt
bashparser-0.17.dist-info/top_level.txt
bashparser-0.17.dist-info/RECORD
